{

	"Robin": {"workouts": [
		{
			"id": "workout1",
			"stat": "as",
			"title": "Robin's Toned Arms",
			"exercise1": "Bicep Curl",
			"exercise2": "Standing Bicep Curl"	,
			"exercise3": "Tricep Dips"	,
			"exercise4": "Shoulder Raises"	,
			"exercise5": "Shoulder Press"			
		},
		{
			"id": "workout2",
			"stat": "ts",
			"title": "Robin's Tough Torso",
			"exercise1": "Inclined Dumbbell Press",
			"exercise2": "Cable Chest Press"	,
			"exercise3": "Wide Push Ups"	,
			"exercise4": "Bench Press"	,
			"exercise5": "Barbell Incline Bench Press"			
		},
		{
			"id": "workout3",
			"stat": "ls",
			"title": "Robin's Wiry Legs",
			"exercise1": "Alternating Lunges",
			"exercise2": "Bicycles"	,
			"exercise3": "Single Leg Deadlift"	,
			"exercise4": "Alternating Step Back Lunge Row"	,
			"exercise5": "Calf Raises"			
		},
		{
			"id": "workout4",
			"stat": "c",
			"title": "Robin's Quick Cardio",
			"exercise1": "Jumping Jacks",
			"exercise2": "Knee High Running"	,
			"exercise3": "Butt Kicks"	,
			"exercise4": "All Around The World"	,
			"exercise5": "Mountain Climbers"			
		}
	]},

	"Catwoman": {"workouts": [
		{
			"id": "workout1",
			"stat": "as",
			"title": "CatWoman Slim Arms",
			"exercise1": "Bicep Curl",
			"exercise2": "Standing Bicep Curl"	,
			"exercise3": "Tricep Dips"	,
			"exercise4": "Shoulder Raises"	,
			"exercise5": "Shoulder Press"			
		},
		{
			"id": "workout2",
			"stat": "ts",
			"title": "CatWoman Torso",
			"exercise1": "Inclined Dumbbell Press",
			"exercise2": "Cable Chest Press"	,
			"exercise3": "Dumbbell Flyes"	,
			"exercise4": "Bench Press"	,
			"exercise5": "Barbell Incline Bench Press"			
		},
		{
			"id": "workout3",
			"stat": "ls",
			"title": "CatWoman Powerful Legs",
			"exercise1": "Alternating Lunges",
			"exercise2": "Leg Press"	,
			"exercise3": "Barbell Squats"	,
			"exercise4": "Dumbbell Squats"	,
			"exercise5": "Calf Raises"			
		},
		{
			"id": "workout4",
			"stat": "c",
			"title": "CatWoman Cardio",
			"exercise1": "Arm Raises",
			"exercise2": "Shoulder Raises"	,
			"exercise3": "Boxing"	,
			"exercise4": "Bicep Curls"	,
			"exercise5": "Tricep Dips"			
		}
	]},

		"Cyborg": {"workouts": [
		{
			"id": "workout1",
			"stat": "as",
			"title": "Cyborg's Massive Arms",
			"exercise1": "Two-Arm Dumbbell Preacher Curl",
			"exercise2": "Bent-Arm Barbell Pullover"	,
			"exercise3": "Diamond Push Ups"	,
			"exercise4": "Seated Alternating Bicep Curls"	,
			"exercise5": "Standing Overhead Barbell Triceps"			
		},
		{
			"id": "workout2",
			"stat": "ts",
			"title": "Cyborg's Metal Torso",
			"exercise1": "Inclined Dumbbell Press",
			"exercise2": "Cable Chest Press"	,
			"exercise3": "Dumbbell Flyes"	,
			"exercise4": "Bench Press"	,
			"exercise5": "Barbell Incline Bench Press"			
		},
		{
			"id": "workout3",
			"stat": "ls",
			"title": "Cyborg's Buff Legs",
			"exercise1": "Walking Lunges",
			"exercise2": "Leg Press"	,
			"exercise3": "Barbell Squats"	,
			"exercise4": "Split Squat"	,
			"exercise5": "Dumbbell Step Up"			
		},
		{
			"id": "workout4",
			"stat": "c",
			"title": "Cyborg's Speedy Cardio",
			"exercise1": "Jump Squats",
			"exercise2": "Step-Up onto Chair"	,
			"exercise3": "Jump Rope"	,
			"exercise4": "Ski Jumps"	,
			"exercise5": "In-Out Push Up Jumps"			
		}
	]},

	"Batman": {"workouts": [
		{
			"id": "workout1",
			"stat": "as",
			"title": "Batman's Arms and Wings",
			"exercise1": "Bicep Curl",
			"exercise2": "Standing Bicep Curl"	,
			"exercise3": "Tricep Dips"	,
			"exercise4": "Shoulder Raises"	,
			"exercise5": "Shoulder Press"			
		},
		{
			"id": "workout2",
			"stat": "ts",
			"title": "Batman's Massive Chest",
			"exercise1": "Inclined Dumbbell Press",
			"exercise2": "Cable Chest Press"	,
			"exercise3": "Dumbbell Flyes"	,
			"exercise4": "Bench Press"	,
			"exercise5": "Barbell Incline Bench Press"			
		},
		{
			"id": "workout3",
			"stat": "ls",
			"title": "Batman's Bat Legs",
			"exercise1": "Deadlift",
			"exercise2": "Single Leg Deadlift"	,
			"exercise3": "Jump Squat"	,
			"exercise4": "Dumbbell Squats"	,
			"exercise5": "Barbell Calf Raises"			
		},
		{
			"id": "workout4",
			"stat": "c",
			"title": "Batman's Swift Cardio",
			"exercise1": "Cable Rows",
			"exercise2": "Jumping Jacks"	,
			"exercise3": "Plank"	,
			"exercise4": "Burpees"	,
			"exercise5": "Run in place"			
		}
	]},
	"Superman": {"workouts": [
		{
			"id": "workout1",
			"stat": "as",
			"title": "Superman's Arms and Wings",
			"exercise1": "Bicep Curl",
			"exercise2": "Standing Bicep Curl"	,
			"exercise3": "Tricep Dips"	,
			"exercise4": "Shoulder Raises"	,
			"exercise5": "Shoulder Press"			
		},
		{
			"id": "workout2",
			"stat": "ts",
			"title": "Superman's Massive Chest",
			"exercise1": "Inclined Dumbbell Press",
			"exercise2": "Cable Chest Press"	,
			"exercise3": "Dumbbell Flyes"	,
			"exercise4": "Bench Press"	,
			"exercise5": "Barbell Incline Bench Press"			
		},
		{
			"id": "workout3",
			"stat": "ls",
			"title": "Superman's Legs",
			"exercise1": "Deadlift",
			"exercise2": "Single Leg Deadlift"	,
			"exercise3": "Jump Squat"	,
			"exercise4": "Dumbbell Squats"	,
			"exercise5": "Barbell Calf Raises"			
		},
		{
			"id": "workout4",
			"stat": "c",
			"title": "Superman's Swift Cardio",
			"exercise1": "Cable Rows",
			"exercise2": "Jumping Jacks"	,
			"exercise3": "Plank"	,
			"exercise4": "Burpees"	,
			"exercise5": "Run in place"			
		}
	]},

	"TwoFace": {"workouts": [
		{
			"id": "workout1",
			"stat": "as",
			"title": "TwoFace Arms",
			"exercise1": "Bicep Curl",
			"exercise2": "Standing Bicep Curl"	,
			"exercise3": "Tricep Dips"	,
			"exercise4": "Shoulder Raises"	,
			"exercise5": "Shoulder Press"			
		},
		{
			"id": "workout2",
			"stat": "ts",
			"title": "TwoFace Torso",
			"exercise1": "Inclined Dumbbell Press",
			"exercise2": "Cable Chest Press"	,
			"exercise3": "Wide Push Ups"	,
			"exercise4": "Bench Press"	,
			"exercise5": "Barbell Incline Bench Press"			
		},
		{
			"id": "workout3",
			"stat": "ls",
			"title": "TwoFace Legs",
			"exercise1": "Alternating Lunges",
			"exercise2": "Bicycles"	,
			"exercise3": "Single Leg Deadlift"	,
			"exercise4": "Alternating Step Back Lunge Row"	,
			"exercise5": "Calf Raises"			
		},
		{
			"id": "workout4",
			"stat": "c",
			"title": "TwoFace Cardio",
			"exercise1": "Jumping Jacks",
			"exercise2": "Knee High Running"	,
			"exercise3": "Butt Kicks"	,
			"exercise4": "All Around The World"	,
			"exercise5": "Mountain Climbers"			
		}
	]},

	"Riddler": {"workouts": [
		{
			"id": "workout1",
			"stat": "as",
			"title": "Riddler's Amazing Arms",
			"exercise1": "Two-Arm Dumbbell Preacher Curl",
			"exercise2": "Bent-Arm Barbell Pullover"	,
			"exercise3": "Diamond Push Ups"	,
			"exercise4": "Seated Alternating Bicep Curls"	,
			"exercise5": "Standing Overhead Barbell Triceps"			
		},
		{
			"id": "workout2",
			"stat": "ts",
			"title": "Riddler's Tough Torso",
			"exercise1": "Inclined Dumbbell Press",
			"exercise2": "Cable Chest Press"	,
			"exercise3": "Dumbbell Flyes"	,
			"exercise4": "Bench Press"	,
			"exercise5": "Barbell Incline Bench Press"				
		},
		{
			"id": "workout3",
			"stat": "ls",
			"title": "Riddler's Kickin Legs",
			"exercise1": "Walking Lunges",
			"exercise2": "Leg Press"	,
			"exercise3": "Barbell Squats"	,
			"exercise4": "Split Squat"	,
			"exercise5": "Dumbbell Step Up"				
		},
		{
			"id": "workout4",
			"stat": "c",
			"title": "Riddler's Rapid Cardio",
			"exercise1": "Cable Rows",
			"exercise2": "Jumping Jacks"	,
			"exercise3": "Plank"	,
			"exercise4": "Burpees"	,
			"exercise5": "Run in place"			
		}
	]},

	"Bane": {"workouts": [
		{
			"id": "workout1",
			"stat": "as",
			"title": "Bane's Massive Arms",
			"exercise1": "Two-Arm Dumbbell Preacher Curl",
			"exercise2": "Bent-Arm Barbell Pullover"	,
			"exercise3": "Diamond Push Ups"	,
			"exercise4": "Seated Alternating Bicep Curls"	,
			"exercise5": "Standing Overhead Barbell Triceps"			
		},
		{
			"id": "workout2",
			"stat": "ts",
			"title": "Bane's Metal Torso",
			"exercise1": "Inclined Dumbbell Press",
			"exercise2": "Cable Chest Press"	,
			"exercise3": "Dumbbell Flyes"	,
			"exercise4": "Bench Press"	,
			"exercise5": "Barbell Incline Bench Press"			
		},
		{
			"id": "workout3",
			"stat": "ls",
			"title": "Bane's Buff Legs",
			"exercise1": "Walking Lunges",
			"exercise2": "Leg Press"	,
			"exercise3": "Barbell Squats"	,
			"exercise4": "Split Squat"	,
			"exercise5": "Dumbbell Step Up"			
		},
		{
			"id": "workout4",
			"stat": "c",
			"title": "Bane's Speedy Cardio",
			"exercise1": "Jump Squats",
			"exercise2": "Step-Up onto Chair"	,
			"exercise3": "Jump Rope"	,
			"exercise4": "Ski Jumps"	,
			"exercise5": "In-Out Push Up Jumps"			
		}
	]},
	"Darkseid": {"workouts": [
		{
			"id": "workout1",
			"stat": "as",
			"title": "Darkseid's Massive Arms",
			"exercise1": "Two-Arm Dumbbell Preacher Curl",
			"exercise2": "Bent-Arm Barbell Pullover"	,
			"exercise3": "Diamond Push Ups"	,
			"exercise4": "Seated Alternating Bicep Curls"	,
			"exercise5": "Standing Overhead Barbell Triceps"			
		},
		{
			"id": "workout2",
			"stat": "ts",
			"title": "Darkseid's Stone Torso",
			"exercise1": "Inclined Dumbbell Press",
			"exercise2": "Cable Chest Press"	,
			"exercise3": "Dumbbell Flyes"	,
			"exercise4": "Bench Press"	,
			"exercise5": "Barbell Incline Bench Press"			
		},
		{
			"id": "workout3",
			"stat": "ls",
			"title": "Darkseid's Buff Legs",
			"exercise1": "Walking Lunges",
			"exercise2": "Leg Press"	,
			"exercise3": "Barbell Squats"	,
			"exercise4": "Split Squat"	,
			"exercise5": "Dumbbell Step Up"			
		},
		{
			"id": "workout4",
			"stat": "c",
			"title": "Darkseid's Speedy Cardio",
			"exercise1": "Jump Squats",
			"exercise2": "Step-Up onto Chair"	,
			"exercise3": "Jump Rope"	,
			"exercise4": "Ski Jumps"	,
			"exercise5": "In-Out Push Up Jumps"			
		}
	]},

	"Joker": {"workouts": [
		{
			"id": "workout1",
			"stat": "as",
			"title": "Joker's Lean Arms",
			"exercise1": "Bicep Curl",
			"exercise2": "Standing Bicep Curl"	,
			"exercise3": "Tricep Dips"	,
			"exercise4": "Shoulder Raises"	,
			"exercise5": "Shoulder Press"			
		},
		{
			"id": "workout2",
			"stat": "ts",
			"title": "Joker's Sturdy Chest",
			"exercise1": "Inclined Dumbbell Press",
			"exercise2": "Cable Chest Press"	,
			"exercise3": "Wide Push Ups"	,
			"exercise4": "Bench Press"	,
			"exercise5": "Barbell Incline Bench Press"			
		},
		{
			"id": "workout3",
			"stat": "ls",
			"title": "Joker's Toned Legs",
			"exercise1": "Alternating Lunges",
			"exercise2": "Bicycles"	,
			"exercise3": "Single Leg Deadlift"	,
			"exercise4": "Alternating Step Back Lunge Row"	,
			"exercise5": "Calf Raises"			
		},
		{
			"id": "workout4",
			"stat": "c",
			"title": "Joker's Swift Cardio",
			"exercise1": "Jumping Jacks",
			"exercise2": "Knee High Running"	,
			"exercise3": "Butt Kicks"	,
			"exercise4": "All Around The World"	,
			"exercise5": "Mountain Climbers"			
		}
	]},

	"stats": [
		{
			"class": "strength",
			"title": "Arm and Shoulder",
			"level": 1,
			"percent": 25		
		},
		{
			"class": "strength",
			"title": "Torso",
			"level": 2,
			"percent": 10		
		},
		{
			"class": "strength",
			"title": "Leg",
			"level": 1,
			"percent": 60		
		},
		{
			"class": "endurance",
			"title": "Arm and Shoulder",
			"level": 2,
			"percent": 30		
		},
		{
			"class": "endurance",
			"title": "Torso",
			"level": 1,
			"percent": 80		
		},
		{
			"class": "endurance",
			"title": "Leg",
			"level": 2,
			"percent": 50		
		}
	]
}